odoo/addons/pos_environment/README.rst
odoo/addons/pos_environment/__init__.py
odoo/addons/pos_environment/__manifest__.py
odoo/addons/pos_environment/i18n/fr.po
odoo/addons/pos_environment/i18n/pos_environment.pot
odoo/addons/pos_environment/models/__init__.py
odoo/addons/pos_environment/models/pos_config.py
odoo/addons/pos_environment/readme/CONFIGURE.rst
odoo/addons/pos_environment/readme/CONTRIBUTORS.rst
odoo/addons/pos_environment/readme/DESCRIPTION.rst
odoo/addons/pos_environment/readme/USAGE.rst
odoo/addons/pos_environment/static/description/icon.png
odoo/addons/pos_environment/static/description/index.html
odoo/addons/pos_environment/static/description/pos_config_form.png
odoo/addons/pos_environment/static/description/receipt.png
odoo/addons/pos_environment/static/src/js/models.js
odoo/addons/pos_environment/static/src/xml/pos_environment.xml
odoo/addons/pos_environment/views/templates.xml
odoo/addons/pos_environment/views/view_pos_config.xml
odoo12_addon_pos_environment-12.0.1.0.1.dist-info/METADATA
odoo12_addon_pos_environment-12.0.1.0.1.dist-info/WHEEL
odoo12_addon_pos_environment-12.0.1.0.1.dist-info/top_level.txt
odoo12_addon_pos_environment-12.0.1.0.1.dist-info/RECORD
