Metadata-Version: 2.1
Name: odoo12-addon-pos-environment
Version: 12.0.1.0.1
Summary: Custom messages on the bill depending on the environment
Home-page: https://github.com/oca/server-env
Author: GRAP,Odoo Community Association (OCA)
Author-email: support@odoo-community.org
License: AGPL-3
Platform: UNKNOWN
Classifier: Programming Language :: Python
Classifier: Framework :: Odoo
Classifier: License :: OSI Approved :: GNU Affero General Public License v3
Requires-Python: >=3.5
Requires-Dist: odoo12-addon-server-environment
Requires-Dist: odoo (<12.1dev,>=12.0a)
